grocery_list/__init__.py
grocery_list/grocery_list.py
grocery_list/ingredients.py
grocery_list/recipes.py
grocery_list-0.0.4.dist-info/LICENSE
grocery_list-0.0.4.dist-info/METADATA
grocery_list-0.0.4.dist-info/WHEEL
grocery_list-0.0.4.dist-info/top_level.txt
grocery_list-0.0.4.dist-info/RECORD
