Metadata-Version: 2.1
Name: grocery-list
Version: 0.0.4
Summary: grocery_list
Home-page: https://github.com/mdmould/grocery_list
Author: Matthew Mould
Author-email: mattdmould@gmail.com
License: MIT
Requires-Python: >=3.7
License-File: LICENSE
